{
  "_format": "hh-sol-cache-2",
  "files": {
    "C:\\Users\\krpra\\Desktop\\ETH+AVAX MODULE 4\\DegenToken\\contracts\\DegenToken.sol": {
      "lastModificationDate": 1690820737046,
      "contentHash": "1cd43a5ea4d4a1f1939a83952283d612",
      "sourceName": "contracts/DegenToken.sol",
      "solcConfig": {
        "version": "0.8.0",
        "settings": {
          "optimizer": {
            "enabled": true,
            "runs": 200
          },
          "outputSelection": {
            "*": {
              "*": [
                "abi",
                "evm.bytecode",
                "evm.deployedBytecode",
                "evm.methodIdentifiers",
                "metadata"
              ],
              "": [
                "ast"
              ]
            }
          }
        }
      },
      "imports": [
        "@openzeppelin/contracts/token/ERC20/ERC20.sol",
        "@openzeppelin/contracts/access/Ownable.sol",
        "@openzeppelin/contracts/token/ERC20/extensions/ERC20Burnable.sol",
        "hardhat/console.sol"
      ],
      "versionPragmas": [
        "^0.8.0"
      ],
      "artifacts": [
        "DegenToken"
      ]
    },
    "C:\\Users\\krpra\\Desktop\\ETH+AVAX MODULE 4\\DegenToken\\node_modules\\@openzeppelin\\contracts\\access\\Ownable.sol": {
      "lastModificationDate": 1690503715689,
      "contentHash": "5a20b2cad87ddb61c7a3a6af21289e28",
      "sourceName": "@openzeppelin/contracts/access/Ownable.sol",
      "solcConfig": {
        "version": "0.8.0",
        "settings": {
          "optimizer": {
            "enabled": true,
            "runs": 200
          },
          "outputSelection": {
            "*": {
              "*": [
                "abi",
                "evm.bytecode",
                "evm.deployedBytecode",
                "evm.methodIdentifiers",
                "metadata"
              ],
              "": [
                "ast"
              ]
            }
          }
        }
      },
      "imports": [
        "../utils/Context.sol"
      ],
      "versionPragmas": [
        "^0.8.0"
      ],
      "artifacts": [
        "Ownable"
      ]
    },
    "C:\\Users\\krpra\\Desktop\\ETH+AVAX MODULE 4\\DegenToken\\node_modules\\@openzeppelin\\contracts\\token\\ERC20\\extensions\\ERC20Burnable.sol": {
      "lastModificationDate": 1690503715270,
      "contentHash": "a1c7f80ae26f5b2d7d563475627fbf25",
      "sourceName": "@openzeppelin/contracts/token/ERC20/extensions/ERC20Burnable.sol",
      "solcConfig": {
        "version": "0.8.0",
        "settings": {
          "optimizer": {
            "enabled": true,
            "runs": 200
          },
          "outputSelection": {
            "*": {
              "*": [
                "abi",
                "evm.bytecode",
                "evm.deployedBytecode",
                "evm.methodIdentifiers",
                "metadata"
              ],
              "": [
                "ast"
              ]
            }
          }
        }
      },
      "imports": [
        "../ERC20.sol",
        "../../../utils/Context.sol"
      ],
      "versionPragmas": [
        "^0.8.0"
      ],
      "artifacts": [
        "ERC20Burnable"
      ]
    },
    "C:\\Users\\krpra\\Desktop\\ETH+AVAX MODULE 4\\DegenToken\\node_modules\\@openzeppelin\\contracts\\utils\\Context.sol": {
      "lastModificationDate": 1690503715165,
      "contentHash": "5f2c5c4b6af2dd4551027144797bc8be",
      "sourceName": "@openzeppelin/contracts/utils/Context.sol",
      "solcConfig": {
        "version": "0.8.0",
        "settings": {
          "optimizer": {
            "enabled": true,
            "runs": 200
          },
          "outputSelection": {
            "*": {
              "*": [
                "abi",
                "evm.bytecode",
                "evm.deployedBytecode",
                "evm.methodIdentifiers",
                "metadata"
              ],
              "": [
                "ast"
              ]
            }
          }
        }
      },
      "imports": [],
      "versionPragmas": [
        "^0.8.0"
      ],
      "artifacts": [
        "Context"
      ]
    },
    "C:\\Users\\krpra\\Desktop\\ETH+AVAX MODULE 4\\DegenToken\\node_modules\\@openzeppelin\\contracts\\token\\ERC20\\ERC20.sol": {
      "lastModificationDate": 1690503715269,
      "contentHash": "3ae5166c6827a9cf1a7a462d1632b464",
      "sourceName": "@openzeppelin/contracts/token/ERC20/ERC20.sol",
      "solcConfig": {
        "version": "0.8.0",
        "settings": {
          "optimizer": {
            "enabled": true,
            "runs": 200
          },
          "outputSelection": {
            "*": {
              "*": [
                "abi",
                "evm.bytecode",
                "evm.deployedBytecode",
                "evm.methodIdentifiers",
                "metadata"
              ],
              "": [
                "ast"
              ]
            }
          }
        }
      },
      "imports": [
        "./IERC20.sol",
        "./extensions/IERC20Metadata.sol",
        "../../utils/Context.sol"
      ],
      "versionPragmas": [
        "^0.8.0"
      ],
      "artifacts": [
        "ERC20"
      ]
    },
    "C:\\Users\\krpra\\Desktop\\ETH+AVAX MODULE 4\\DegenToken\\node_modules\\@openzeppelin\\contracts\\token\\ERC20\\IERC20.sol": {
      "lastModificationDate": 1690503715569,
      "contentHash": "df36f7051335cd1e748b1b6463b7fdd3",
      "sourceName": "@openzeppelin/contracts/token/ERC20/IERC20.sol",
      "solcConfig": {
        "version": "0.8.0",
        "settings": {
          "optimizer": {
            "enabled": true,
            "runs": 200
          },
          "outputSelection": {
            "*": {
              "*": [
                "abi",
                "evm.bytecode",
                "evm.deployedBytecode",
                "evm.methodIdentifiers",
                "metadata"
              ],
              "": [
                "ast"
              ]
            }
          }
        }
      },
      "imports": [],
      "versionPragmas": [
        "^0.8.0"
      ],
      "artifacts": [
        "IERC20"
      ]
    },
    "C:\\Users\\krpra\\Desktop\\ETH+AVAX MODULE 4\\DegenToken\\node_modules\\@openzeppelin\\contracts\\token\\ERC20\\extensions\\IERC20Metadata.sol": {
      "lastModificationDate": 1690503715576,
      "contentHash": "909ab67fc5c25033fe6cd364f8c056f9",
      "sourceName": "@openzeppelin/contracts/token/ERC20/extensions/IERC20Metadata.sol",
      "solcConfig": {
        "version": "0.8.0",
        "settings": {
          "optimizer": {
            "enabled": true,
            "runs": 200
          },
          "outputSelection": {
            "*": {
              "*": [
                "abi",
                "evm.bytecode",
                "evm.deployedBytecode",
                "evm.methodIdentifiers",
                "metadata"
              ],
              "": [
                "ast"
              ]
            }
          }
        }
      },
      "imports": [
        "../IERC20.sol"
      ],
      "versionPragmas": [
        "^0.8.0"
      ],
      "artifacts": [
        "IERC20Metadata"
      ]
    },
    "C:\\Users\\krpra\\Desktop\\ETH+AVAX MODULE 4\\DegenToken\\node_modules\\hardhat\\console.sol": {
      "lastModificationDate": 1690503656761,
      "contentHash": "e2884fb4e1ef4b4a7c7ac3a227880b0f",
      "sourceName": "hardhat/console.sol",
      "solcConfig": {
        "version": "0.8.0",
        "settings": {
          "optimizer": {
            "enabled": true,
            "runs": 200
          },
          "outputSelection": {
            "*": {
              "*": [
                "abi",
                "evm.bytecode",
                "evm.deployedBytecode",
                "evm.methodIdentifiers",
                "metadata"
              ],
              "": [
                "ast"
              ]
            }
          }
        }
      },
      "imports": [],
      "versionPragmas": [
        ">= 0.4.22 <0.9.0"
      ],
      "artifacts": [
        "console"
      ]
    }
  }
}
